CPU/Registers.v
module Registers (
    input wire clk,                // Clock signal
    input wire reset,              // Reset signal
    input wire we,                 // Write enable
    input wire [4:0] ra1,          // Read address 1
    input wire [4:0] ra2,          // Read address 2
    input wire [4:0] wa,           // Write address
    input wire [31:0] wd,          // Write data
    output wire [31:0] rd1,        // Read data 1
    output wire [31:0] rd2         // Read data 2
);
    // Declare the register file as an array of 32 32-bit registers
    reg [31:0] registers [31:0];

    // Read operation (combinational)
    assign rd1 = (ra1 == 5'd0) ? 32'd0 : registers[ra1]; // Read register x0 always returns 0
    assign rd2 = (ra2 == 5'd0) ? 32'd0 : registers[ra2]; // Read register x0 always returns 0

    // Write operation (sequential)
    always @(posedge clk or posedge reset) begin
        if (reset) begin
            // Reset all registers to 0 (optional)
            integer i;
            for (i = 0; i < 32; i = i + 1) begin
                registers[i] <= 32'd0;
            end
        end else if (we && (wa != 5'd0)) begin
            // Write to the register (except x0)
            registers[wa] <= wd;
        end
    end
endmodule

CPU/testbench/Registers_tb.v
module Registers_tb;
    // Inputs
    reg clk;
    reg reset;
    reg we;
    reg [4:0] ra1;
    reg [4:0] ra2;
    reg [4:0] wa;
    reg [31:0] wd;

    // Outputs
    wire [31:0] rd1;
    wire [31:0] rd2;

    // Instantiate the Registers module
    Registers uut (
        .clk(clk),
        .reset(reset),
        .we(we),
        .ra1(ra1),
        .ra2(ra2),
        .wa(wa),
        .wd(wd),
        .rd1(rd1),
        .rd2(rd2)
    );

    // Clock generation
    always #11 clk = ~clk;

    initial begin
        // Initialize Inputs
        clk = 0;
        reset = 1;
        we = 0;
        ra1 = 0;
        ra2 = 0;
        wa = 0;
        wd = 0;

        // Open VCD file for GTKWave
        $dumpfile("Registers_tb.vcd");
        $dumpvars(0, Registers_tb);

        // Wait 10 ns for global reset to finish
        #10;
        reset = 0;

        // Write to register 1
        we = 1;
        wa = 5'd1;
        wd = 32'hAAAA_BBBB;
        #10;

        // Write to register 2
        wa = 5'd2;
        wd = 32'hCCCC_DDDD;
        #10;

        // Disable write enable
        we = 0;

        // Read from register 1
        ra1 = 5'd1;
        #10;
        if (rd1 !== 32'hAAAA_BBBB) $display("Test Failed: Read from register 1");
        #5;
        // Read from register 2
        ra2 = 5'd2;
        #10;
        if (rd2 !== 32'hCCCC_DDDD) $display("Test Failed: Read from register 2");

        // Ensure register x0 always returns 0
        ra1 = 5'd0;
        ra2 = 5'd0;
        #10;
        if (rd1 !== 32'h0000_0000 || rd2 !== 32'h0000_0000) $display("Test Failed: Read from register x0");

        // Write to register x0 (should have no effect)
        we = 1;
        wa = 5'd0;
        wd = 32'hFFFF_FFFF;
        #10;
        we = 0;
        ra1 = 5'd0;
        #10;
        if (rd1 !== 32'h0000_0000) $display("Test Failed: Write to register x0");
        
        $display("All tests passed");
        $stop;
    end
endmodule

CPU/testbench/Registers_tb.vcd
$date
	Fri Jul  5 04:15:41 2024
$end
$version
	Icarus Verilog
$end
$timescale
	1s
$end
$scope module Registers_tb $end
$var wire 32 ! rd2 [31:0] $end
$var wire 32 " rd1 [31:0] $end
$var reg 1 # clk $end
$var reg 5 $ ra1 [4:0] $end
$var reg 5 % ra2 [4:0] $end
$var reg 1 & reset $end
$var reg 5 ' wa [4:0] $end
$var reg 32 ( wd [31:0] $end
$var reg 1 ) we $end
$scope module uut $end
$var wire 1 # clk $end
$var wire 5 * ra1 [4:0] $end
$var wire 5 + ra2 [4:0] $end
$var wire 1 & reset $end
$var wire 5 , wa [4:0] $end
$var wire 32 - wd [31:0] $end
$var wire 1 ) we $end
$var wire 32 . rd2 [31:0] $end
$var wire 32 / rd1 [31:0] $end
$var integer 32 0 i [31:0] $end
$upscope $end
$upscope $end
$enddefinitions $end
$comment Show the parameter values. $end
$dumpall
$end
#0
$dumpvars
b100000 0
b0 /
b0 .
b0 -
b0 ,
b0 +
b0 *
0)
b0 (
b0 '
1&
b0 %
b0 $
0#
b0 "
b0 !
$end
#10
b10101010101010101011101110111011 (
b10101010101010101011101110111011 -
b1 '
b1 ,
1)
0&
#11
1#
#20
b11001100110011001101110111011101 (
b11001100110011001101110111011101 -
b10 '
b10 ,
#22
0#
#30
b10101010101010101011101110111011 "
b10101010101010101011101110111011 /
b1 $
b1 *
0)
#33
1#
#44
0#
#45
b10 %
b10 +
#55
b0 "
b0 /
b0 %
b0 +
b0 $
b0 *
1#
#65
b11111111111111111111111111111111 (
b11111111111111111111111111111111 -
b0 '
b0 ,
1)
#66
0#
#75
0)
